clod.py
clod-0.10.0.data/scripts/clod.py
clod-0.10.0.dist-info/LICENSE
clod-0.10.0.dist-info/METADATA
clod-0.10.0.dist-info/WHEEL
clod-0.10.0.dist-info/top_level.txt
clod-0.10.0.dist-info/RECORD
