Metadata-Version: 2.1
Name: clod
Version: 0.10.0
Summary: Create and recursively fill a temporary directory
Home-page: https://github.com/rec/clod
Author: Tom Ritchford
Author-email: tom@swirly.com
License: MIT
Keywords: testing,modules
Platform: UNKNOWN
Classifier: Development Status :: 4 - Beta
Classifier: Programming Language :: Python :: 3.4
Classifier: Programming Language :: Python :: 3.5
Classifier: Programming Language :: Python :: 3.6
Classifier: Programming Language :: Python :: 3.7
Classifier: Programming Language :: Python :: 3.8
Classifier: Intended Audience :: Developers
Classifier: License :: OSI Approved :: MIT License
Classifier: Topic :: Software Development :: Libraries
Classifier: Topic :: Utilities
Requires-Dist: dek
